neologism/__init__.py
neologism/dcfg.py
neologism/py.typed
neologism/rule.py
neologism/utils.py
neologism/yacc.py
neologism-0.0.8.dist-info/LICENSE
neologism-0.0.8.dist-info/METADATA
neologism-0.0.8.dist-info/WHEEL
neologism-0.0.8.dist-info/top_level.txt
neologism-0.0.8.dist-info/RECORD
