Metadata-Version: 2.1
Name: neologism
Version: 0.0.8
Summary: Dynamically modifiable context-free grammar written in python
Home-page: https://github.com/alltilla/neologism
Author: Attila Szakacs
Author-email: szakacs.attila96@gmail.com
Project-URL: Bug Tracker, https://github.com/alltilla/neologism/issues
Project-URL: Documentation, https://neologism.readthedocs.io/
Classifier: Programming Language :: Python :: 3
Classifier: License :: OSI Approved :: GNU General Public License v3 or later (GPLv3+)
Classifier: Operating System :: OS Independent
License-File: LICENSE
Requires-Dist: networkx
